utils_hoo/__init__.py
utils_hoo/_pkg_info.py
utils_hoo/install_check.py
utils_hoo/utils_MultiProcess.py
utils_hoo/utils_MultiThread.py
utils_hoo/utils_datetime.py
utils_hoo/utils_general.py
utils_hoo/utils_io.py
utils_hoo/BackPacks/BackPack01_Float_Dy.py
utils_hoo/BackPacks/BackPack01_Int_Dy.py
utils_hoo/BackPacks/__init__.py
utils_hoo/FindAddends/FindAddends_BackPack01Float.py
utils_hoo/FindAddends/FindAddends_BackPack01Int.py
utils_hoo/FindAddends/FindAddends_BigFirst.py
utils_hoo/FindAddends/FindAddends_Recu.py
utils_hoo/FindAddends/FindAddends_SmlFirst.py
utils_hoo/FindAddends/FindAddends_utils.py
utils_hoo/FindAddends/__init__.py
utils_hoo/Sorts/__init__.py
utils_hoo/Sorts/bubble_sort.py
utils_hoo/Sorts/bucket_sort.py
utils_hoo/Sorts/insert_sort.py
utils_hoo/Sorts/insert_sort_bin.py
utils_hoo/Sorts/quick_sort.py
utils_hoo/tmp/CRR.py
utils_hoo/tmp/CtrlPreTS.py
utils_hoo/tmp/NPairSum.py
utils_hoo/tmp/PIDtest.py
utils_hoo/tmp/PIDtest2.py
utils_hoo/tmp/VMD.py
utils_hoo/tmp/__init__.py
utils_hoo/tmp/cca_test.py
utils_hoo/tmp/cumvar.py
utils_hoo/tmp/dtw_test.py
utils_hoo/tmp/explore.py
utils_hoo/tmp/gini.py
utils_hoo/tmp/merge_sort.py
utils_hoo/tmp/mouse_move.py
utils_hoo/tmp/mpc_test1.py
utils_hoo/tmp/options_Implied_volatility.py
utils_hoo/tmp/pf_test.py
utils_hoo/tmp/plot_test.py
utils_hoo/tmp/plot_test2.py
utils_hoo/tmp/simple_smooth.py
utils_hoo/tmp/test_AES.py
utils_hoo/tmp/test_AES_CBC.py
utils_hoo/tmp/test_AES_ECB.py
utils_hoo/tmp/test_AES_ECB2.py
utils_hoo/tmp/test_backtrader.py
utils_hoo/tmp/test_code.py
utils_hoo/tmp/test_find_peaks.py
utils_hoo/tmp/test_get_var_name.py
utils_hoo/tmp/test_lr.py
utils_hoo/tmp/test_ocr.py
utils_hoo/tmp/test_pywechat.py
utils_hoo/tmp/test_twinx.py
utils_hoo/tmp/tfDNNCls_test.py
utils_hoo/tmp/tmp.py
utils_hoo/tmp/tmp_args.py
utils_hoo/tmp/transformer_pytorch.py
utils_hoo/tmp/utils_SignalDec.py
utils_hoo/tmp/utils_TimeSeries.py
utils_hoo/tmp/utils_lottery.py
utils_hoo/tmp/utils_rl.py
utils_hoo/tmp/utils_rl2.py
utils_hoo-0.1.17.dist-info/METADATA
utils_hoo-0.1.17.dist-info/WHEEL
utils_hoo-0.1.17.dist-info/top_level.txt
utils_hoo-0.1.17.dist-info/RECORD
