Metadata-Version: 2.1
Name: utils-hoo
Version: 0.1.17
Summary: Genlovy Hoo's utils.
Home-page: https://pypi.org/project/utils-hoo/
Author: Genlovy Hoo, YueYong Hu
Author-email: genlovhyy@163.com
License: MPL 2.0
Platform: any
